README.md
setup.py
json2toml/__init__.py
json2toml/cli.py
json2toml.egg-info/PKG-INFO
json2toml.egg-info/SOURCES.txt
json2toml.egg-info/dependency_links.txt
json2toml.egg-info/entry_points.txt
json2toml.egg-info/not-zip-safe
json2toml.egg-info/requires.txt
json2toml.egg-info/top_level.txt